crawlerhelper/__init__.py
crawlerhelper/crawlerHelper.py
crawlerHelper-0.0.1.dist-info/LICENSE
crawlerHelper-0.0.1.dist-info/METADATA
crawlerHelper-0.0.1.dist-info/WHEEL
crawlerHelper-0.0.1.dist-info/top_level.txt
crawlerHelper-0.0.1.dist-info/RECORD
