Metadata-Version: 2.1
Name: crawlerHelper
Version: 0.0.1
Summary: tools which can easy the process of making crawler
Home-page: https://gitlab.com/snippets/1873717
Author: Wyatt Huang
Author-email: p@hty.email
License: UNKNOWN
Platform: UNKNOWN
Classifier: Programming Language :: Python :: 3
Classifier: License :: OSI Approved :: MIT License
Classifier: Operating System :: OS Independent
